gdrivelab/__init__.py
gdrivelab/toc.py
gdrivelab-0.1.14.dist-info/LICENSE.txt
gdrivelab-0.1.14.dist-info/METADATA
gdrivelab-0.1.14.dist-info/WHEEL
gdrivelab-0.1.14.dist-info/top_level.txt
gdrivelab-0.1.14.dist-info/RECORD
